mcp_rong_gettime/__init__.py
mcp_rong_gettime/server.py
mcp_rong_gettime-0.1.0.dist-info/METADATA
mcp_rong_gettime-0.1.0.dist-info/WHEEL
mcp_rong_gettime-0.1.0.dist-info/top_level.txt
mcp_rong_gettime-0.1.0.dist-info/RECORD
